wannier90io/__about__.py
wannier90io/__init__.py
wannier90io/__main__.py
wannier90io/_amn.py
wannier90io/_chk.py
wannier90io/_core.py
wannier90io/_eig.py
wannier90io/_mmn.py
wannier90io/_nnkp.py
wannier90io/_schema.py
wannier90io/_win.py
wannier90io/_wout.py
wannier90io-0.1.0b1.dist-info/METADATA
wannier90io-0.1.0b1.dist-info/WHEEL
wannier90io-0.1.0b1.dist-info/entry_points.txt
wannier90io-0.1.0b1.dist-info/licenses/LICENSE
wannier90io-0.1.0b1.dist-info/RECORD
