Metadata-Version: 2.1
Name: wannier90io
Version: 0.1.0b1
Summary: A Python library for Wannier90 I/O
Project-URL: Documentation, https://github.com/jimustafa/wannier90io-python#readme
Project-URL: Issues, https://github.com/jimustafa/wannier90io-python/issues
Project-URL: Source, https://github.com/jimustafa/wannier90io-python
Author: Jamal I. Mustafa
License: MIT License
License-File: LICENSE
Classifier: License :: OSI Approved :: MIT License
Classifier: Programming Language :: Python :: 3
Requires-Python: >=3.8
Requires-Dist: numpy
Requires-Dist: pydantic
